LICENSE
MANIFEST.in
README.rst
setup.cfg
setup.py
tests/__init__.py
tests/test_js.py
tw2/__init__.py
tw2.excanvas.egg-info/PKG-INFO
tw2.excanvas.egg-info/SOURCES.txt
tw2.excanvas.egg-info/dependency_links.txt
tw2.excanvas.egg-info/entry_points.txt
tw2.excanvas.egg-info/namespace_packages.txt
tw2.excanvas.egg-info/not-zip-safe
tw2.excanvas.egg-info/requires.txt
tw2.excanvas.egg-info/top_level.txt
tw2/excanvas/__init__.py
tw2/excanvas/base.py
tw2/excanvas/static/excanvas.min.js